versioning_utils/__init__.py
versioning_utils/__version__.py
versioning_utils/utils/__init__.py
versioning_utils/utils/constants.py
versioning_utils/utils/git.py
versioning_utils/utils/metadata.py
versioning_utils/utils/version.py
promidius_versioning_utils-0.0.4.dist-info/METADATA
promidius_versioning_utils-0.0.4.dist-info/WHEEL
promidius_versioning_utils-0.0.4.dist-info/top_level.txt
promidius_versioning_utils-0.0.4.dist-info/RECORD
