Metadata-Version: 2.1
Name: promidius-versioning-utils
Version: 0.0.4
Summary: A simple versioning utility for Python projects.
Author-email: ThePromidius <thepromidiusyt@gmail.com>
Project-URL: Homepage, https://github.com/ThePromidius/versioning-utils
Project-URL: Issues, https://github.com/ThePromidius/versioning-utils/issues
Classifier: Programming Language :: Python :: 3
Classifier: License :: OSI Approved :: MIT License
Classifier: Operating System :: OS Independent
Requires-Python: >=3.11
Requires-Dist: packaging
